EloquentJavascript2e/README.md
EloquentJavascript2e/__init__.py
EloquentJavascript2e/__main__.py
EloquentJavascript2e/file.epub
EloquentJavascript2e/index.html
EloquentJavascript2e/css/__init__.py
EloquentJavascript2e/css/annotations.css
EloquentJavascript2e/css/main.css
EloquentJavascript2e/css/normalize.css
EloquentJavascript2e/css/popup.css
EloquentJavascript2e/font/__init__.py
EloquentJavascript2e/font/fontello.eot
EloquentJavascript2e/font/fontello.svg
EloquentJavascript2e/font/fontello.ttf
EloquentJavascript2e/font/fontello.woff
EloquentJavascript2e/img/__init__.py
EloquentJavascript2e/img/annotator-glyph-sprite.png
EloquentJavascript2e/img/annotator-icon-sprite.png
EloquentJavascript2e/img/apple-touch-icon.png
EloquentJavascript2e/img/cancelfullscreen.png
EloquentJavascript2e/img/close.png
EloquentJavascript2e/img/fullscreen.png
EloquentJavascript2e/img/loader.gif
EloquentJavascript2e/img/menu-icon.png
EloquentJavascript2e/img/save.png
EloquentJavascript2e/img/saved.png
EloquentJavascript2e/img/settings-s.png
EloquentJavascript2e/img/settings.png
EloquentJavascript2e/img/star.png
EloquentJavascript2e/js/__init__.py
EloquentJavascript2e/js/epub.js
EloquentJavascript2e/js/epub.min.js
EloquentJavascript2e/js/epub.min.map
EloquentJavascript2e/js/hooks.min.js
EloquentJavascript2e/js/hooks.min.map
EloquentJavascript2e/js/reader.js
EloquentJavascript2e/js/reader.js.map
EloquentJavascript2e/js/reader.min.js
EloquentJavascript2e/js/reader.min.map
EloquentJavascript2e/js/hooks/__init__.py
EloquentJavascript2e/js/hooks/extensions/__init__.py
EloquentJavascript2e/js/hooks/extensions/highlight.js
EloquentJavascript2e/js/libs/__init__.py
EloquentJavascript2e/js/libs/jquery.min.js
EloquentJavascript2e/js/libs/localforage.min.js
EloquentJavascript2e/js/libs/screenfull.js
EloquentJavascript2e/js/libs/screenfull.min.js
EloquentJavascript2e/js/libs/zip.min.js
EloquentJavascript2e/js/plugins/__init__.py
EloquentJavascript2e/js/plugins/hypothesis.js
eloquent_javascript_2e-2024.3.1.0.dist-info/METADATA
eloquent_javascript_2e-2024.3.1.0.dist-info/WHEEL
eloquent_javascript_2e-2024.3.1.0.dist-info/entry_points.txt
eloquent_javascript_2e-2024.3.1.0.dist-info/top_level.txt
eloquent_javascript_2e-2024.3.1.0.dist-info/RECORD
